{
  "id": "1581708",
  "name": "easy-do",
  "font_family": "iconfont",
  "css_prefix_text": "icon-",
  "description": "",
  "glyphs": [
    {
      "icon_id": "448351",
      "name": "项目",
      "font_class": "project",
      "unicode": "e60c",
      "unicode_decimal": 58892
    },
    {
      "icon_id": "675257",
      "name": "最大化",
      "font_class": "maxmum-bak",
      "unicode": "e662",
      "unicode_decimal": 58978
    },
    {
      "icon_id": "1917124",
      "name": "编辑",
      "font_class": "edit",
      "unicode": "e7fd",
      "unicode_decimal": 59389
    },
    {
      "icon_id": "1995617",
      "name": "好友",
      "font_class": "user",
      "unicode": "e606",
      "unicode_decimal": 58886
    },
    {
      "icon_id": "2589945",
      "name": "todo-task",
      "font_class": "todo",
      "unicode": "e625",
      "unicode_decimal": 58917
    },
    {
      "icon_id": "3378483",
      "name": "任务",
      "font_class": "task",
      "unicode": "eadc",
      "unicode_decimal": 60124
    },
    {
      "icon_id": "3708455",
      "name": "最大化",
      "font_class": "to-open",
      "unicode": "e777",
      "unicode_decimal": 59255
    },
    {
      "icon_id": "4031889",
      "name": "最小化",
      "font_class": "to-close",
      "unicode": "e6d6",
      "unicode_decimal": 59094
    },
    {
      "icon_id": "5213510",
      "name": "消息",
      "font_class": "message",
      "unicode": "e603",
      "unicode_decimal": 58883
    },
    {
      "icon_id": "5930263",
      "name": "最小化",
      "font_class": "to-close2",
      "unicode": "e60e",
      "unicode_decimal": 58894
    },
    {
      "icon_id": "6754193",
      "name": "关 闭",
      "font_class": "close",
      "unicode": "e62a",
      "unicode_decimal": 58922
    },
    {
      "icon_id": "7160395",
      "name": "最大化",
      "font_class": "maxmum",
      "unicode": "e61a",
      "unicode_decimal": 58906
    },
    {
      "icon_id": "7352827",
      "name": "右向箭头",
      "font_class": "right-arrow",
      "unicode": "e670",
      "unicode_decimal": 58992
    },
    {
      "icon_id": "7352828",
      "name": "左向箭头",
      "font_class": "left-arrow",
      "unicode": "e671",
      "unicode_decimal": 58993
    },
    {
      "icon_id": "12818665",
      "name": "plus",
      "font_class": "plus",
      "unicode": "e7e5",
      "unicode_decimal": 59365
    },
    {
      "icon_id": "12818667",
      "name": "reduce",
      "font_class": "minimum",
      "unicode": "e7e6",
      "unicode_decimal": 59366
    },
    {
      "icon_id": "12818682",
      "name": "check",
      "font_class": "check",
      "unicode": "e7e8",
      "unicode_decimal": 59368
    },
    {
      "icon_id": "12859534",
      "name": "撤销",
      "font_class": "reback",
      "unicode": "e649",
      "unicode_decimal": 58953
    }
  ]
}
